pdfsearch/__init__.py
pdfsearch/pdfs.py
pdfsearch-0.0.1.data/scripts/pdfs.py
pdfsearch-0.0.1.dist-info/LICENSE
pdfsearch-0.0.1.dist-info/METADATA
pdfsearch-0.0.1.dist-info/WHEEL
pdfsearch-0.0.1.dist-info/top_level.txt
pdfsearch-0.0.1.dist-info/RECORD
