Metadata-Version: 2.1
Name: pdfsearch
Version: 0.0.1
Summary: pdf - Search Tool, searches for a keyword in the filename            ,the n first pages of the file or in the keyword section of the metadata.
Home-page: https://gitlab.com/_HolgerW/pdfs.git
Author: Holger Wasmund
Author-email: Holger.Wasmund@gmail.com
License: UNKNOWN
Platform: UNKNOWN
Classifier: License :: OSI Approved :: MIT License
Classifier: Programming Language :: Python :: 3
Requires-Python: >=3.5.5
Requires-Dist: argparse
Requires-Dist: pdfminer.six
Requires-Dist: pathlib
